MANIFEST.in
README.rst
setup.py
datio/__init__.py
datio/core.py
datio.egg-info/PKG-INFO
datio.egg-info/SOURCES.txt
datio.egg-info/dependency_links.txt
datio.egg-info/top_level.txt
datio/tests/test_core.py