Metadata-Version: 1.0
Name: datio
Version: 0.0.1
Summary: 
